LICENSE
MANIFEST.in
Makefile
README.rst
genzshcomp.py
pyproject.toml
setup.py
genzshcomp.egg-info/PKG-INFO
genzshcomp.egg-info/SOURCES.txt
genzshcomp.egg-info/dependency_links.txt
genzshcomp.egg-info/entry_points.txt
genzshcomp.egg-info/not-zip-safe
genzshcomp.egg-info/top_level.txt
test/test_genzshcomp.py