Metadata-Version: 1.1
Name: genzshcomp
Version: 0.6.0
Summary: Automatic generated to zsh completion function, for Python's Option Parser Modules.
Home-page: http://bitbucket.org/hhatto/genzshcomp/
Author: Hideo Hattori
Author-email: hhatto.jp@gmail.com
License: New BSD License
Keywords: auto automation bash zsh completion
Platform: UNKNOWN
Classifier: Development Status :: 4 - Beta
Classifier: Intended Audience :: Developers
Classifier: Environment :: Console
Classifier: Operating System :: Unix
Classifier: License :: OSI Approved :: BSD License
Classifier: Programming Language :: Python
Classifier: Programming Language :: Python :: 2
Classifier: Programming Language :: Python :: 3
Classifier: Programming Language :: Unix Shell
Classifier: Topic :: System :: Shells
